{
    "combined_responses": [
        "{\"page6_text\": \"公司名稱\\n台天水泥股份有限公司\\n合併綜合損益表\\n民國111年1月1日至3月31日\\n（稅後資料之核准）\\n單位: 除每股盈餘為新台幣元外，其為仟元\\n會計年度\\n111年1月1日至3月31日\\n110年1月1日至3月31日\\n代碼\\n項目\\n金額\\n百分比\\n金額\\n百分比\\n4000\\n營業收入（附註三二）\\n$22,973,467\\n100\\n$22,037,652\\n100\\n5000\\n營業成本（附註十二、一二、二四及三一）\\n20,977,100\\n91\\n16,512,812\\n75\\n5900\\n營業毛利\\n1,996,361\\n9\\n5,524,840\\n25\\n營業費用（附註三二、二四及三二）\\n6100\\n推銷費用\\n202,622\\n1\\n173,130\\n1\\n6200\\n管理費用\\n1,448,902\\n6\\n1,144,134\\n5\\n6300\\n研究發展費用\\n137,214\\n1\\n-\\n-\\n6000\\n營業費用合計\\n1,788,738\\n8\\n1,317,264\\n6\\n6900\\n營業淨利\\n207,623\\n1\\n4,207,576\\n19\\n營業外收入及支出\\n7060\\n採用權益法核列之關聯企業及合資損益份額（附註十四）\\n622,247\\n3\\n714,592\\n3\\n7100\\n利息收入\\n372,039\\n1\\n354,116\\n2\\n7130\\n股利收入\\n405,293\\n2\\n-\\n-\\n7190\\n其他收入\\n81,506\\n-\\n135,434\\n1\\n7210\\n處分不動產、廠房及設備利益（損失）\\n37,346\\n-\\n(5,574)\\n-\\n7630\\n外幣兌換淨益（損）\\n404,744\\n2\\n(21,281)\\n-\\n7050\\n財務成本（附註二四）\\n(525,210)\\n(2)\\n(417,888)\\n(2)\\n7590\\n其他支出\\n(191,246)\\n(1)\\n(107,774)\\n(1)\\n7635\\n透過損益按公允價值衡量金融資產及負債之淨損\\n(242,231)\\n(1)\\n(4,128)\\n-\\n7000\\n營業外收入及支出合計\\n964,488\\n4\\n647,497\\n3\\n（接次頁）\\n- 6 -\"}",
        "{\n    \"page8_text\": \"（承前頁）\\n\\n代碼  綜合損益總額歸屬於\\n8710 未公司業主           $ 10,317,964        45%     $ 2,621,147        12%\\n8720 非控制權益            (217,133)       (1%)      416,066          2%\\n8700 合計                  $ 10,100,831       44%     $ 3,037,213       14%\\n\\n每股盈餘（附註二六）\\n     來自繼續營業單位及停業單位\\n9750 基本                 $ 0.20            $ 0.57\\n9850 稀釋                 $ 0.20            $ 0.55\\n\\n     來自繼續營業單位\\n9710 基本                 $ 0.20            $ 0.57\\n9810 稀釋                 $ 0.20            $ 0.55\\n\\n後附之附註係本合併財務報告之一部分。\\n（請參閱勤業眾信聯合會計師事務所民國 111 年 5 月 10 日核閱報告）\\n\\n董事長：張安平\\n經理人：李鐘培\\n會計主管：葉國宏\\n\\n- 8 -\"\n}",
        "\n{\n    \"page7_text\": \"（承前頁）\\n\\n代碼   111年1月1日至3月31日   110年1月1日至3月31日\\n\\n7900 繼續營業單位稅前淨利\\n     金額     %   金額     %\\n     $1,172,111   5   $4,855,073   22\\n\\n7950 所得稅費用（附註二五）\\n     315,605   1   1,113,682   5\\n\\n8000 繼續營業單位本期淨利\\n     856,506   4   3,741,391   17\\n\\n8100 停業單位損失（附註十一）\\n     —   —   (11,154)   —\\n\\n8200 本期淨利\\n     856,506   4   3,730,237   17\\n\\n本期其他綜合損益淨額（附註二三）\\n\\n8310 不重分類至損益之項目：\\n     8316 透過其他綜合損益按公允價值衡量之權益工具投資未實現評價損益\\n     588,133   3   851,853   4\\n\\n8320 採用權益法認列之關聯企業及合資之其他綜合損益之份額\\n     45,410   —   91,778   —\\n\\n     633,543   3   943,631   4\\n\\n8360  後續可能重分類至損益之項目：\\n     8361 國外營運機構財務報表換算之兌換差額\\n     7,655,591   33   (105,125)   —\\n\\n8370 採用權益法認列之關聯企業及合資之其他綜合損益份額\\n     955,191   4   (1,531,530)   (7)\\n\\n     8,610,782   37   (1,636,655)   (7)\\n\\n8300 其他綜合損益淨額\\n     9,244,325   40   (693,024)   (3)\\n\\n8500 本期綜合損益總額\\n     $10,100,831   44   $3,037,213   14\\n\\n淨利歸屬於\\n\\n8610 本公司業主\\n     $1,204,144   5   $3,318,974   15\\n\\n8620 非控制權益\\n     (347,638)   (1)   411,263   2\\n\\n8600 $856,506   4   $3,730,237   17\\n\\n（接次頁）\"\n}"
    ],
    "raw_text": ""
}